LICENSE
README.md
setup.py
CommitLog.egg-info/PKG-INFO
CommitLog.egg-info/SOURCES.txt
CommitLog.egg-info/dependency_links.txt
CommitLog.egg-info/top_level.txt
bin/commitlog-sign-cert
commitlog/__init__.py
commitlog/append.py
commitlog/purge.py
commitlog/rpc.py
commitlog/server.py
commitlog/tail.py