Metadata-Version: 2.1
Name: CommitLog
Version: 20231127
Summary: General Purpose Distributed Commit Log - Replicated and Strongly Consistent
Home-page: https://github.com/magicray/CommitLog
Author: Bhupendra Singh
Author-email: bhsingh@gmail.com
Keywords: paxos,consistent,replicated,commit,log
License-File: LICENSE
